docks/__init__.py
docks/base_image.py
docks/cli.py
docks/files.py
docks/generate_doc.py
docks/ports.py
docks/utils.py
docks/variables.py
docks-0.1.13.dist-info/LICENSE
docks-0.1.13.dist-info/METADATA
docks-0.1.13.dist-info/WHEEL
docks-0.1.13.dist-info/entry_points.txt
docks-0.1.13.dist-info/RECORD
