Metadata-Version: 2.1
Name: docks
Version: 0.1.13
Summary: A simple automatic Dockerfile documentation generator
Author: gianfaProm
Author-email: gianfrancesco.angelini@prometeia.com
Requires-Python: >=3.9,<4.0
Classifier: Programming Language :: Python :: 3
Classifier: Programming Language :: Python :: 3.9
Classifier: Programming Language :: Python :: 3.10
Classifier: Programming Language :: Python :: 3.11
Classifier: Programming Language :: Python :: 3.12
Classifier: Programming Language :: Python :: 3.13
Requires-Dist: click (>=8.1.7,<9.0.0)
